helikite/__init__.py
helikite/classes/__init__.py
helikite/classes/cleaning.py
helikite/constants.py
helikite/helikite.py
helikite/instruments/__init__.py
helikite/instruments/base.py
helikite/instruments/cpc3007.py
helikite/instruments/filter.py
helikite/instruments/flight_computer.py
helikite/instruments/mcda_instrument.py
helikite/instruments/mcpc.py
helikite/instruments/msems.py
helikite/instruments/ozone.py
helikite/instruments/pico.py
helikite/instruments/pops.py
helikite/instruments/smart_tether.py
helikite/instruments/stap.py
helikite/instruments/tapir.py
helikite/metadata/__init__.py
helikite/metadata/models.py
helikite/metadata/utils.py
helikite/plots.py
helikite/processing/__init__.py
helikite/processing/conversions.py
helikite/processing/helpers.py
helikite/processing/post/TandRH.py
helikite/processing/post/__init__.py
helikite/processing/post/altitude.py
helikite/processing/post/co2.py
helikite/processing/post/crosscorrelation.py
helikite/processing/post/level1.py
helikite/processing/post/level2.py
helikite/processing/post/outliers.py
helikite/processing/post/tools.py
helikite/processing/post/wind.py
helikite/processing/preprocess.py
helikite/processing/sorting.py
helikite/tests/cli/__init.__.py
helikite/tests/cli/test_commands.py
helikite/tests/cli/test_execute.py
helikite/tests/cli/test_generate_config.py
helikite/tests/cli/test_pipeline.py
helikite/tests/cli/test_preprocess_cli.py
helikite/tests/cli/test_version.py
helikite/tests/conftest.py
helikite/tests/instruments/test_base_instrument.py
helikite/tests/instruments/test_flight_computer_v2.py
helikite/tests/instruments/test_smart_tether.py
helikite/tests/metadata/test_load.py
helikite/tests/process/level0/__init__.py
helikite/tests/process/level0/conftest.py
helikite/tests/process/level0/mock.py
helikite/tests/process/level0/test_campaigns.py
helikite/tests/process/level0/test_core.py
helikite/tests/process/level0/test_crosscorrelation.py
helikite/tests/process/level0/test_dependencies.py
helikite_data_processing-1.1.3.dist-info/METADATA
helikite_data_processing-1.1.3.dist-info/WHEEL
helikite_data_processing-1.1.3.dist-info/entry_points.txt
helikite_data_processing-1.1.3.dist-info/RECORD
