Metadata-Version: 2.1
Name: helikite-data-processing
Version: 1.1.3
Summary: Library to generate quicklooks and data quality checks on Helikite campaigns
Author: Evan Thomas
Author-email: evan.thomas@epfl.ch
Requires-Python: >=3.11,<3.13
Classifier: Programming Language :: Python :: 3
Classifier: Programming Language :: Python :: 3.11
Classifier: Programming Language :: Python :: 3.12
Requires-Dist: autodoc-pydantic (>=2.2.0,<3.0.0)
Requires-Dist: ipympl (>=0.9.4,<0.10.0)
Requires-Dist: ipywidgets (>=8.1.5,<9.0.0)
Requires-Dist: jupyterlab (>=4.2.5,<5.0.0)
Requires-Dist: jupyterlab-widgets (>=3.0.13,<4.0.0)
Requires-Dist: matplotlib (>=3.7.1,<4.0.0)
Requires-Dist: orjson (>=3.10.15,<4.0.0)
Requires-Dist: pandas (>=2.2,<3.0)
Requires-Dist: plotly (>=5.13.1,<6.0.0)
Requires-Dist: pyarrow (>=19.0.1,<20.0.0)
Requires-Dist: pydantic-settings (>=2.5.2,<3.0.0)
Requires-Dist: pyyaml (>=6.0,<7.0)
Requires-Dist: scipy (>=1.10.1,<2.0.0)
Requires-Dist: sphinx (>=8.2.3,<9.0.0)
Requires-Dist: sphinx-autoapi (>=3.6.0,<4.0.0)
Requires-Dist: sphinx-rtd-theme (>=3.0.2,<4.0.0)
Requires-Dist: toml (>=0.10.2,<0.11.0)
Requires-Dist: typer (>=0.12.5,<0.13.0)
Requires-Dist: types-pyyaml (>=6.0.12.9,<7.0.0.0)
